submissions/lab/LAB04/nsa325_nishant_aswani_lab04/code/mux.v
// File: mux.v
// Name: Nishant Aswani
// Instructor: Cristoforos Vasilatos
// Course: Computer Organization and Architecture (ENGR-UH 3511) Fall 2019
// Due: Sep 25 2019

`ifndef MUX_V
`define MUX_V

module mux #(parameter N=32) (inA, inB, out, select);

  // input wires
  input wire [N-1: 0] inA;
  input wire [N-1: 0] inB;
  input wire select;

  // output wire
  output wire [N-1: 0] out;

  // output selection using unary operator
  assign out = select? inB : inA;

endmodule

`endif

submissions/lab/LAB04/nsa325_nishant_aswani_lab04/code/data-memory.v
// File: data-memory.v
// Name: Nishant Aswani
// Instructor: Cristoforos Vasilatos
// Course: Computer Organization and Architecture (ENGR-UH 3511) Fall 2019
// Due: Sep 18 2019

`ifndef DATA_MEMORY_V
`define DATA_MEMORY_V

module data_memory(clk,
                  address,
                  readData,
                  writeData,
                  memWrite,
                  memRead);

  input wire clk;               // clock
  input wire [31:0] address;     // input address for data location
  output wire [31:0] readData;  // value stored at address
  input wire [31:0] writeData;  // value to write into address

  input wire memWrite;          // enable flag for writing
  input wire memRead;           // enable flag for reading

  reg [31:0] mem[127:0];        // 2D array to store dummy values

  initial begin
    mem[0] <= 32'h1CEB00DA;  //  0x1CEB00DA (icebooda)
    mem[1] <= 32'hBAAAAAAD;  //  0xBAAAAAAD (baaaaaad)
    mem[2] <= 32'hBADDCAFE;  //  0xBADDCAFE (baddcafe)
    mem[3] <= 32'hCAFED00D;  //  0xCAFED00D (cafedude)
    mem[4] <= 32'hDEADDEAD;  //  0xDEADDEAD (deaddead)
    mem[5] <= 32'hFACEFEED;  //  0xFACEFEED (facefeed)
    mem[6] <= 32'hC00010FF;  //  0xC00010FF (cooloff)
    mem[7] <= 32'h50D1EB0B;  //  0x50D1EB0B (sodiebob)

  end

  // at every positive edge of the clock
  always @(posedge clk) begin
    // if memWrite is enabled
		if (memWrite == 1) begin
      // write the value to given register address
			mem[address] = writeData;
		end
	end

  // if memRead is enabled, read address at location, otherwise output 0
  assign readData = memRead ? mem[address[4:0]][31:0] : 0;





endmodule




`endif

submissions/lab/LAB04/nsa325_nishant_aswani_lab04/code/alu.v
// File: alu.v
// Name: Nishant Aswani
// Instructor: Cristoforos Vasilatos
// Course: Computer Organization and Architecture (ENGR-UH 3511) Fall 2019
// Due: Sep 25 2019

`ifndef ALU_V
`define ALU_V

module alu(clk, inA, inB, funct, zero, out);

  input wire clk;         // clock
  input wire [31:0] inA;  // input A
  input wire [31:0] inB;  // input B
  input wire [3:0] funct; // function code to decide ALU operation

  output reg [31:0] out;  // resulting value from operation
  output wire zero;       // zero flag

  always @(*) begin
    case (funct)
      4'b0000 : out <= inA & inB; // code 0 does a bitwise and
      4'b0001 : out <= inA | inB; // code 1 does a bitwise or
      4'b0010 : out <= inA + inB; // code 2 does addition
      4'b0011 : out <= inA - inB; // code 3 does subtraction
      4'b0100 : out <= inA ^ inB; // code 4 does a bitwise xor
    endcase
  end

  assign zero = (out==0) ? 1:0;   // if out == 0, then raise zero flag

endmodule
`endif

submissions/lab/LAB04/nsa325_nishant_aswani_lab04/code/shift-left-2.v
// File: shift-left-2.v
// Name: Nishant Aswani
// Instructor: Cristoforos Vasilatos
// Course: Computer Organization and Architecture (ENGR-UH 3511) Fall 2019
// Due: Sep 25 2019

`ifndef SHIFT_LEFT_2_V
`define SHIFT_LEFT_2_V

module shift_left_2 (clk, in, out);

// input wires
input wire [31:0] in;
input wire clk;

//output wires
output reg [31:0] out;

always@(*) begin
  out <= in<<2;
end

endmodule

`endif

submissions/lab/LAB04/nsa325_nishant_aswani_lab04/code/sign-extend.v
// File: sign-extend.v
// Name: Nishant Aswani
// Instructor: Cristoforos Vasilatos
// Course: Computer Organization and Architecture (ENGR-UH 3511) Fall 2019
// Due: Sep 25 2019

`ifndef SIGN_EXTEND_V
`define SIGN_EXTEND_V

module sign_extend (in, out);

  // input wires
  input wire [15:0] in;
  // input wire clk;

  //output wires
  output reg [31:0] out;

  always@(*) begin
    out <= { {16{in[15]}}, in[15:0] };
  end

endmodule

`endif

submissions/lab/LAB04/nsa325_nishant_aswani_lab04/code/register-file.v
// File: register-file.v
// Name: Nishant Aswani
// Instructor: Cristoforos Vasilatos
// Course: Computer Organization and Architecture (ENGR-UH 3511) Fall 2019
// Due: Sep 25 2019

`ifndef REGISTER_FILE_V
`define REGISTER_FILE_V

module register_file(clk,
                    rst,
                    readRegisterOne,
                    readRegisterTwo,
                    writeRegister,
                    writeData,
                    writeEnable,
                    readDataOne,
                    readDataTwo);

  input wire clk; //  clock
  input wire rst; //  async reset
  input wire [4:0] readRegisterOne; //  address for first read register
  input wire [4:0] readRegisterTwo; //  address for second read register
  input wire [4:0] writeRegister;   //  address for write register
  input wire [31:0] writeData;      //  data to be written into write register
  input wire writeEnable;           //  enable flag to change register

  output reg [31:0] readDataOne;   //  data to be sent to ALU
  output reg [31:0] readDataTwo;   //  data to be sent to ALU

  reg [31:0] reg_file[31:0];       //  registers stored in register file

  integer i = 0;

  // initialization block
  initial begin
    // use a for loop to reset all register values to zero
    for(i=0; i<31; i=i+1) begin
      reg_file[i] <= 32'd0; // set back to 0
    end

  end

  // block for resetting
  always@(posedge clk) begin

    // if reset is enabled
    if (rst == 1) begin
      // use a for loop to reset all register values to zero
      for(i=0; i<31; i=i+1) begin
        reg_file[i] <= 32'd0; // set back to 0
     	end
      reg_file[9] <= 32'h00000001;
      reg_file[10] <= 32'hDEADDEAD;
    end

    // else check for write conditions
    // and store writeData into appropriate register
    else if (writeRegister && writeEnable != 0) begin
        reg_file[writeRegister][31:0] <= writeData;
    end
  end


  // @(*) used for combinational logic
  // assigning output value
  always @ (*) begin
    // if read address is 0, then output 0
    if(readRegisterOne == 5'd0) begin
      readDataOne = 32'd0;
    end

    // otherwise output whatever is actually inside
    else begin
      readDataOne = reg_file[readRegisterOne][31:0];
    end

  end

  always @ (*) begin
    // if read address is 0, then output 0
    if(readRegisterTwo == 5'd0) begin
      readDataTwo = 32'd0;
    end

    // otherwise output whatever is actually inside
    else begin
      readDataTwo = reg_file[readRegisterTwo][31:0];
    end

  end

endmodule

`endif

submissions/lab/LAB04/nsa325_nishant_aswani_lab04/code/instruction-memory.v
// File: instruction-memory.v
// Name: Nishant Aswani
// Instructor: Cristoforos Vasilatos
// Course: Computer Organization and Architecture (ENGR-UH 3511) Fall 2019
// Due: Sep 25 2019

`ifndef INSTRUCTION_MEMORY_V
`define INSTRUCTION_MEMORY_V

module instruction_memory (clk,readAddress, instruction);

  input wire clk;
  input wire [31:0] readAddress;  // address for instruction
  output reg [31:0] instruction; // instruction at address

  reg [31:0] mem[31:0]; //32 by 32 bit instruction memory

  initial begin

    ///////////////////////////// PROGRAM 1 /////////////////////////////////
    // mem[0] <= 32'b000000_00000_00000_0000000000000000;    // EMPTY
    // mem[1] <= 32'b001000_01001_01001_0000000000000001;    //ADDI $t1 $t1 1
    // mem[2] <= 32'b001000_01010_01010_0000000000000010;    //ADDI $t2 $t2 2
    // mem[3] <= 32'b001000_01001_01001_0000000000000001;    //ADDI $t1 $t1 1
    // mem[4] <= 32'b001000_01010_01010_0000000000000010;    //ADDI $t2 $t2 2

    ///////////////////////////// PROGRAM 2 /////////////////////////////////
    mem[0] <= 32'b000000_00000_00000_0000000000000000;    // EMPTY
    mem[1] <= 32'b101011_01001_01010_0000000000000000;    //SW $t2 0($t1)
    mem[2] <= 32'b100011_01001_01001_0000000000000000;    //LW $t1 0($t1)

  end

  always@(posedge clk) begin
    //assign relevant instruction given the register memory
    instruction <= mem[readAddress[31:2]][31:0];
  end

endmodule

`endif

submissions/lab/LAB04/nsa325_nishant_aswani_lab04/code/program-counter.v
// File: program-counter.v
// Name: Nishant Aswani
// Instructor: Cristoforos Vasilatos
// Course: Computer Organization and Architecture (ENGR-UH 3511) Fall 2019
// Due: Sep 25 2019

`ifndef PROGRAM_COUNTER_V
`define PROGRAM_COUNTER_V

module program_counter (clk, rst, out, in);

  input wire clk;            //clock
  input wire rst;            //reset
  input wire [31:0] in;      //input address
  output reg [31:0] out;     //output address


  always@(posedge clk) begin

    if (rst) begin
      out <= 32'b0;
    end

    // assign value of in to out
    else begin
      out <= in;
    end
    
  end

endmodule

`endif

submissions/lab/LAB04/nsa325_nishant_aswani_lab04/code/top-level.v
// File: test-bench.v
// Name: Nishant Aswani
// Instructor: Cristoforos Vasilatos
// Course: Computer Organization and Architecture (ENGR-UH 3511) Fall 2019
// Due: Sep 25 2019

`ifndef TOP_LEVEL_V
`define TOP_LEVEL_V

module top_level(clk,rst);

  //////////////
  /// WIRING ///
  //////////////

  // Global
  input wire clk;
  input wire rst;
  wire [31:0] testReg1;
  wire [31:0] testReg2;

  // Control Logic (Hard-Coded)
  ///////// PROGRAM 1 /////////
  // reg RegDst = 0;
  // reg RegWrite = 1;
  // reg ALUSrc = 1;
  // reg [3:0] ALUControl = 4'b0010;
  // reg MemtoReg = 0;
  // reg memWrite = 0;
  // reg memRead = 0;
  // reg PCSrc = 0;

  // Control Logic (Hard-Coded)
  ///////// PROGRAM 2 /////////
  reg RegDst = 0;
  reg RegWrite = 0;
  reg ALUSrc = 1;
  reg [3:0] ALUControl = 4'b0010;
  reg MemtoReg = 1;
  reg memWrite = 0;
  reg memRead = 0;
  reg PCSrc = 0;

  // Program Counter
  reg [31:0] PCin;          // value that goes into PC, gets value from PCnext
  wire [31:0] PCnext;       // wire used for storing PCout + 4
  wire [31:0] PCout;        // value sent to IM
  wire [31:0] PCbranch;     // value used for storing output of PCin and offset
  wire [31:0] PCMUXout;     // value that decides between PCbranch and PCin

  // Instruction Memory
  wire [31:0] IMout;        // instruction from IM

  // Register File
  wire [31:0] RFout1;       // register 1 output
  wire [31:0] RFout2;       // register 2 output
  wire [31:0] RFWriteData;  // data to be written in

  // RegFile Mux
  wire [4:0] RFWriteReg;    // address of register to be written in

  // Sign Extend
  wire [31:0] SextOut;      // result of sign extension

  // Shift Left Logical by 2
  wire [31:0] SLLOut = 32'd0; // result of shift left 2

  // ALU
  wire [31:0] ALUin1;       // argument A for ALU
  wire [31:0] ALUin2;       // argument B for ALU
  wire [31:0] ALUout;       // output from ALU
  wire ALUzero;             // zero flag from ALU

  // Data Memory
  wire [31:0] DMout;        // data read from data memory


  ////////////////////////////
  /// MODULE INSTANTIATION ///
  ////////////////////////////
  program_counter pc(
    .clk(clk),
    .rst(rst),
    .in(PCMUXout),
    .out(PCout)
    );

  instruction_memory im(
    .clk(clk),
    .readAddress(PCout),
    .instruction(IMout)
    );

  mux #(5) immux(
      .inA(IMout[20:16]),
      .inB(IMout[15:11]),
      .out(RFWriteReg),
      .select(RegDst)
    );

  register_file rf(
    .clk(clk),
    .rst(rst),
    .readRegisterOne(IMout[25:21]),
    .readRegisterTwo(IMout[20:16]),
    .writeRegister(RFWriteReg),
    .writeData(RFWriteData),
    .writeEnable(RegWrite),
    .readDataOne(RFout1),
    .readDataTwo(RFout2)
    );

  sign_extend sext(
    .in(IMout[15:0]),
    .out(SextOut)
    );

  shift_left_2 sll(
    .clk(clk),
    .in(SextOut),
    .out(SLLOut)
    );

  mux #(32) alumux(
    .inA(RFout2),
    .inB(SextOut),
    .out(ALUin2),
    .select(ALUSrc)
    );

  alu alu(
    .clk(clk),
    .inA(ALUin1),
    .inB(ALUin2),
    .funct(ALUControl),
    .out(ALUout),
    .zero(ALUzero)
    );

  mux #(32) rfmux(
    .inA(ALUout),
    .inB(DMout),
    .out(RFWriteData),
    .select(MemtoReg)
    );

  data_memory dm(
    .clk(clk),
    .address(ALUout),
    .readData(DMout),
    .writeData(RFout2),
    .memWrite(memWrite),
    .memRead(memRead)
    );
  mux #(32) pcmux(
    .inA(PCin),
    .inB(PCbranch),
    .out(PCMUXout),
    .select(PCSrc)
    );


  ////////////////
  /// PC LOGIC ///
  ////////////////

  // half adder: add 4 to output of PC and send it next
  assign PCnext = PCout + 4;


  always@(*) begin
    // if reset, PCin must be 0
    if (rst) begin
      PCin <= 32'b0;
    end
    // otherwise, transfer the PCnext value to PCin
    else begin
      PCin <= PCnext;
    end
  end

  ////////////////////
  /// BRANCH LOGIC ///
  ////////////////////

  // add the offset to PCin
  assign PCbranch = SLLOut + PCin;

  /////////////////
  /// ALU LOGIC ///
  /////////////////

  assign ALUin1 = RFout1;

  ////////////////
  /// DM LOGIC ///
  ////////////////

  always@(*) begin

    // store word
    if(IMout[31:26] == 6'b101011) begin
      memWrite <= 1;
      memRead <= 0;
      RegWrite = 0;
    end

    // load word
    else if (IMout[31:26] == 6'b100011) begin
      memWrite <= 0;
      memRead <= 1;
      RegWrite = 1;
    end

    else begin
      memWrite <= 0;
      memRead <= 0;
    end

  end

  //////////////////
  /// TEST LOGIC ///
  //////////////////

  // assign testReg1 = rf.reg_file[9];
  // assign testReg2 = rf.reg_file[10];

  assign testReg1 = dm.mem[1];
  assign testReg2 = rf.reg_file[9];




endmodule
`endif

submissions/lab/LAB04/nsa325_nishant_aswani_lab04/code/top-level-tb.v
// File: top-level-tb.v
// Name: Nishant Aswani
// Instructor: Cristoforos Vasilatos
// Course: Computer Organization and Architecture (ENGR-UH 3511) Fall 2019
// Due: Sep 25 2019

`include "top-level.v"

module top_level_tb ();

  reg clk = 1'b0;              // clock
  reg rst = 1'b0;              // reset

  // assign variables
  top_level tl(
    .clk(clk),
    .rst(rst)
    );

  always begin
    #1 clk = ~clk;
  end

  initial begin
    $dumpfile("top-level.vcd");
    $dumpvars(0, top_level_tb);
    rst = 1'b1;
    #5;
    rst = 1'b0;
    #30;
    $finish;
  end
endmodule

submissions/lab/LAB04/nsa325_nishant_aswani_lab04/code/top-level.vcd
$date
	Wed Sep 25 00:52:05 2019
$end
$version
	Icarus Verilog
$end
$timescale
	1s
$end
$scope module top_level_tb $end
$var reg 1 ! clk $end
$var reg 1 " rst $end
$scope module tl $end
$var wire 32 # ALUin1 [31:0] $end
$var wire 32 $ SLLOut [31:0] $end
$var wire 1 ! clk $end
$var wire 1 " rst $end
$var wire 32 % testReg1 [31:0] $end
$var wire 32 & testReg2 [31:0] $end
$var wire 32 ' SextOut [31:0] $end
$var wire 32 ( RFout2 [31:0] $end
$var wire 32 ) RFout1 [31:0] $end
$var wire 5 * RFWriteReg [4:0] $end
$var wire 32 + RFWriteData [31:0] $end
$var wire 32 , PCout [31:0] $end
$var wire 32 - PCnext [31:0] $end
$var wire 32 . PCbranch [31:0] $end
$var wire 32 / PCMUXout [31:0] $end
$var wire 32 0 IMout [31:0] $end
$var wire 32 1 DMout [31:0] $end
$var wire 1 2 ALUzero $end
$var wire 32 3 ALUout [31:0] $end
$var wire 32 4 ALUin2 [31:0] $end
$var reg 4 5 ALUControl [3:0] $end
$var reg 1 6 ALUSrc $end
$var reg 1 7 MemtoReg $end
$var reg 1 8 PCSrc $end
$var reg 32 9 PCin [31:0] $end
$var reg 1 : RegDst $end
$var reg 1 ; RegWrite $end
$var reg 1 < memRead $end
$var reg 1 = memWrite $end
$scope module alu $end
$var wire 1 ! clk $end
$var wire 4 > funct [3:0] $end
$var wire 32 ? inA [31:0] $end
$var wire 1 2 zero $end
$var wire 32 @ inB [31:0] $end
$var reg 32 A out [31:0] $end
$upscope $end
$scope module alumux $end
$var wire 1 6 select $end
$var wire 32 B out [31:0] $end
$var wire 32 C inB [31:0] $end
$var wire 32 D inA [31:0] $end
$upscope $end
$scope module dm $end
$var wire 32 E address [31:0] $end
$var wire 1 ! clk $end
$var wire 1 < memRead $end
$var wire 1 = memWrite $end
$var wire 32 F writeData [31:0] $end
$var wire 32 G readData [31:0] $end
$upscope $end
$scope module im $end
$var wire 1 ! clk $end
$var wire 32 H readAddress [31:0] $end
$var reg 32 I instruction [31:0] $end
$upscope $end
$scope module immux $end
$var wire 5 J inA [4:0] $end
$var wire 5 K inB [4:0] $end
$var wire 1 : select $end
$var wire 5 L out [4:0] $end
$upscope $end
$scope module pc $end
$var wire 1 ! clk $end
$var wire 1 " rst $end
$var wire 32 M in [31:0] $end
$var reg 32 N out [31:0] $end
$upscope $end
$scope module pcmux $end
$var wire 32 O inA [31:0] $end
$var wire 32 P inB [31:0] $end
$var wire 1 8 select $end
$var wire 32 Q out [31:0] $end
$upscope $end
$scope module rf $end
$var wire 1 ! clk $end
$var wire 5 R readRegisterOne [4:0] $end
$var wire 5 S readRegisterTwo [4:0] $end
$var wire 1 " rst $end
$var wire 1 ; writeEnable $end
$var wire 5 T writeRegister [4:0] $end
$var wire 32 U writeData [31:0] $end
$var reg 32 V readDataOne [31:0] $end
$var reg 32 W readDataTwo [31:0] $end
$var integer 32 X i [31:0] $end
$upscope $end
$scope module rfmux $end
$var wire 32 Y inA [31:0] $end
$var wire 32 Z inB [31:0] $end
$var wire 1 7 select $end
$var wire 32 [ out [31:0] $end
$upscope $end
$scope module sext $end
$var wire 16 \ in [15:0] $end
$var reg 32 ] out [31:0] $end
$upscope $end
$scope module sll $end
$var wire 1 ! clk $end
$var wire 32 ^ in [31:0] $end
$var reg 32 _ out [31:0] $end
$upscope $end
$upscope $end
$upscope $end
$enddefinitions $end
#0
$dumpvars
bx _
bx ^
bx ]
bx \
b0 [
b0 Z
bx Y
b11111 X
bx W
bx V
b0 U
bx T
bx S
bx R
b0 Q
bx P
b0 O
bx N
b0 M
bx L
bx K
bx J
bx I
bx H
b0 G
bx F
bx E
bx D
bx C
bx B
bx A
bx @
bx ?
b10 >
0=
0<
0;
0:
b0 9
08
17
16
b10 5
bx 4
bx 3
x2
b0 1
bx 0
b0 /
bx .
bx -
bx ,
b0 +
bx *
bx )
bx (
bx '
b0 &
b10111010101010101010101010101101 %
bx $
bx #
1"
0!
$end
#1
b100 -
b0 ,
b0 H
b0 N
b1 &
b11111 X
1!
#2
0!
#3
12
b0 3
b0 A
b0 E
b0 Y
b0 .
b0 P
b0 $
b0 _
b0 4
b0 @
b0 B
b0 '
b0 C
b0 ]
b0 ^
b0 *
b0 L
b0 T
b0 (
b0 D
b0 F
b0 W
b0 #
b0 ?
b0 )
b0 V
b0 \
b0 S
b0 R
b0 K
b0 J
b1 &
b0 0
b0 I
b11111 X
1!
#4
0!
#5
b100 /
b100 M
b100 Q
b100 .
b100 P
b100 9
b100 O
1!
0"
#6
0!
#7
b1000 /
b1000 M
b1000 Q
b1000 .
b1000 P
b1000 9
b1000 O
b1000 -
b100 ,
b100 H
b100 N
1!
#8
0!
#9
02
b1100 /
b1100 M
b1100 Q
b1 3
b1 A
b1 E
b1 Y
b1100 .
b1100 P
b1100 9
b1100 O
1=
b11011110101011011101111010101101 (
b11011110101011011101111010101101 D
b11011110101011011101111010101101 F
b11011110101011011101111010101101 W
b1 #
b1 ?
b1 )
b1 V
b1010 *
b1010 L
b1010 T
b1010 S
b1001 R
b1010 J
b1100 -
b1000 ,
b1000 H
b1000 N
b10101101001010100000000000000000 0
b10101101001010100000000000000000 I
1!
#10
0!
#11
b11011110101011011101111010101101 +
b11011110101011011101111010101101 U
b11011110101011011101111010101101 [
b11011110101011011101111010101101 1
b11011110101011011101111010101101 G
b11011110101011011101111010101101 Z
b10000 /
b10000 M
b10000 Q
1<
0=
b10000 .
b10000 P
b10000 9
b10000 O
b1 (
b1 D
b1 F
b1 W
b1001 *
b1001 L
b1001 T
b1001 S
b1001 J
1;
b10001101001010010000000000000000 0
b10001101001010010000000000000000 I
b10000 -
b1100 ,
b1100 H
b1100 N
b11011110101011011101111010101101 %
1!
#12
0!
#13
bx00 $
bx00 _
x2
b0 +
b0 U
b0 [
bx 4
bx @
bx B
b10100 /
b10100 M
b10100 Q
b0 1
b0 G
b0 Z
bx '
bx C
bx ]
bx ^
bx 3
bx A
bx E
bx Y
bx .
bx P
b10100 9
b10100 O
0<
bx *
bx L
bx T
bx \
bx S
bx R
bx K
bx J
bx (
bx D
bx F
bx W
bx #
bx ?
bx )
bx V
b10100 -
b10000 ,
b10000 H
b10000 N
bx 0
bx I
b11011110101011011101111010101101 &
1!
#14
0!
#15
b11000 /
b11000 M
b11000 Q
b11000 9
b11000 O
b11000 -
b10100 ,
b10100 H
b10100 N
1!
#16
0!
#17
b11100 /
b11100 M
b11100 Q
b11100 9
b11100 O
b11100 -
b11000 ,
b11000 H
b11000 N
1!
#18
0!
#19
b100000 /
b100000 M
b100000 Q
b100000 9
b100000 O
b100000 -
b11100 ,
b11100 H
b11100 N
1!
#20
0!
#21
b100100 /
b100100 M
b100100 Q
b100100 9
b100100 O
b100100 -
b100000 ,
b100000 H
b100000 N
1!
#22
0!
#23
b101000 /
b101000 M
b101000 Q
b101000 9
b101000 O
b101000 -
b100100 ,
b100100 H
b100100 N
1!
#24
0!
#25
b101100 /
b101100 M
b101100 Q
b101100 9
b101100 O
b101100 -
b101000 ,
b101000 H
b101000 N
1!
#26
0!
#27
b110000 /
b110000 M
b110000 Q
b110000 9
b110000 O
b110000 -
b101100 ,
b101100 H
b101100 N
1!
#28
0!
#29
b110100 /
b110100 M
b110100 Q
b110100 9
b110100 O
b110100 -
b110000 ,
b110000 H
b110000 N
1!
#30
0!
#31
b111000 /
b111000 M
b111000 Q
b111000 9
b111000 O
b111000 -
b110100 ,
b110100 H
b110100 N
1!
#32
0!
#33
b111100 /
b111100 M
b111100 Q
b111100 9
b111100 O
b111100 -
b111000 ,
b111000 H
b111000 N
1!
#34
0!
#35
b1000000 /
b1000000 M
b1000000 Q
b1000000 9
b1000000 O
b1000000 -
b111100 ,
b111100 H
b111100 N
1!
